<?xml version="1.0" encoding="UTF-8"?><!DOCTYPE ImportAction PUBLIC "sailpoint.dtd" "sailpoint.dtd">
<ImportAction name="connectorRegistryUpdateAction">
  <Application connector="sailpoint.connector.LotusDomino" featuresString="PROVISIONING, SYNC_PROVISIONING, ENABLE, AUTHENTICATE, SEARCH, UNLOCK, PASSWORD, CURRENT_PASSWORD" icon="directory2Icon" name="IBM Lotus Domino - Direct" type="IBM Lotus Domino - Direct">
    <Attributes>
      <Map>
        <entry key="formPath" value="LotusDomino.xhtml"/>
      </Map>
    </Attributes>
    <Schemas>
      <Schema displayAttribute="FullName" identityAttribute="NOTEID" nativeObjectType="account" objectType="account">
        <AttributeDefinition name="FirstName" remediationModificationType="None" required="true" type="string">
          <Description>First name of the user</Description>
        </AttributeDefinition>
        <AttributeDefinition name="MiddleInitial" remediationModificationType="None" type="string">
          <Description>Middle initials of the user</Description>
        </AttributeDefinition>
        <AttributeDefinition name="LastName" remediationModificationType="None" required="true" type="string" >
          <Description>Last name of the user</Description>
        </AttributeDefinition>
        <AttributeDefinition name="FullName" remediationModificationType="None" type="string">
          <Description>Full name of the user</Description>
        </AttributeDefinition>
        <AttributeDefinition name="ShortName" remediationModificationType="None" type="string">
          <Description>Short name of the user</Description>
        </AttributeDefinition>
        <AttributeDefinition name="UserName" remediationModificationType="None" type="string">
          <Description>The user full name</Description>
        </AttributeDefinition>
        <AttributeDefinition name="Type" remediationModificationType="None" type="string">
          <Description>The type of the document</Description>
        </AttributeDefinition>
        <AttributeDefinition name="Owner" remediationModificationType="None" type="string">
          <Description>The owner of the document</Description>
        </AttributeDefinition>
        <AttributeDefinition name="MailSystem" remediationModificationType="None" type="string">
          <Description>The type of mail system</Description>
        </AttributeDefinition>
        <AttributeDefinition name="MailDomain" remediationModificationType="None" type="string">
          <Description>Mail domain of the user</Description>
        </AttributeDefinition>
        <AttributeDefinition name="MailServer" remediationModificationType="None" type="string">
          <Description>Mail server of the user</Description>
        </AttributeDefinition>
        <AttributeDefinition name="MailFile" remediationModificationType="None" type="string">
          <Description>Mail file of the user</Description>
        </AttributeDefinition>
        <AttributeDefinition name="InternetAddress" remediationModificationType="None" type="string">
          <Description>Mail internet address</Description>
        </AttributeDefinition>
        <AttributeDefinition name="JobTitle" remediationModificationType="None" type="string">
          <Description>Job title of the user</Description>
        </AttributeDefinition>
        <AttributeDefinition name="CompanyName" remediationModificationType="None" type="string">
          <Description>Company name of the user</Description>
        </AttributeDefinition>
        <AttributeDefinition name="Department" remediationModificationType="None" type="string">
          <Description>Department of the user</Description>
        </AttributeDefinition>
        <AttributeDefinition name="EmployeeID" remediationModificationType="None" type="string">
          <Description>EmployeeID of the user</Description>
        </AttributeDefinition>
        <AttributeDefinition name="Location" remediationModificationType="None" type="string">
          <Description>Location of the user</Description>
        </AttributeDefinition>
        <AttributeDefinition name="Manager" remediationModificationType="None" type="string">
          <Description>Manager of the user</Description>
        </AttributeDefinition>
        <AttributeDefinition name="OfficePhoneNumber" remediationModificationType="None" type="string">
          <Description>Office phone number of the user</Description>
        </AttributeDefinition>
        <AttributeDefinition name="OfficeFAXPhoneNumber " remediationModificationType="None" type="string">
          <Description>Office fax phone number of the user</Description>
        </AttributeDefinition>
        <AttributeDefinition name="CellPhoneNumber" remediationModificationType="None" type="string">
          <Description>Cell phone number of the user</Description>
        </AttributeDefinition>
        <AttributeDefinition name="PhoneNumber_6" remediationModificationType="None" type="string">
          <Description>Phone number_6 of the user</Description>
        </AttributeDefinition>
        <AttributeDefinition name="Assistant" remediationModificationType="None" type="string">
          <Description>Assistant of the user</Description>
        </AttributeDefinition>
        <AttributeDefinition name="OfficeStreetAddress" remediationModificationType="None" type="string">
          <Description>Office street address of the user</Description>
        </AttributeDefinition>
        <AttributeDefinition name="OfficeCity" remediationModificationType="None" type="string">
          <Description>Office city of the user</Description>
        </AttributeDefinition>
        <AttributeDefinition name="OfficeState" remediationModificationType="None" type="string">
          <Description>Office state of the user</Description>
        </AttributeDefinition>
        <AttributeDefinition name="OfficeZIP" remediationModificationType="None" type="string">
          <Description>Office ZIP/Portal of the user</Description>
        </AttributeDefinition>
        <AttributeDefinition name="OfficeCountry" remediationModificationType="None" type="string">
          <Description>Office country of the user</Description>
        </AttributeDefinition>
        <AttributeDefinition name="OfficeNumber" remediationModificationType="None" type="string">
          <Description>Office number of the user</Description>
        </AttributeDefinition>
        <AttributeDefinition name="StreetAddress" remediationModificationType="None" type="string">
          <Description>Street address of the user</Description>
        </AttributeDefinition>
        <AttributeDefinition name="State" remediationModificationType="None" type="string">
          <Description>State of the user</Description>
        </AttributeDefinition>
        <AttributeDefinition name="Zip" remediationModificationType="None" type="string">
          <Description>Zip/Postal code of the user</Description>
        </AttributeDefinition>
        <AttributeDefinition name="Country" remediationModificationType="None" type="string">
          <Description>Country of the user</Description>
        </AttributeDefinition>
        <AttributeDefinition name="PhoneNumber" remediationModificationType="None" type="string">
          <Description>Phone number of the user</Description>
        </AttributeDefinition>
        <AttributeDefinition name="HomeFAXPhoneNumber" remediationModificationType="None" type="string">
          <Description>Home fax phone number of the user</Description>
        </AttributeDefinition>
        <AttributeDefinition name="Spouse" remediationModificationType="None" type="string">
          <Description>Spouse of the user</Description>
        </AttributeDefinition>
        <AttributeDefinition name="Children" remediationModificationType="None" type="string">
          <Description>Children of the user</Description>
        </AttributeDefinition>
        <AttributeDefinition name="PersonalID" remediationModificationType="None" type="string">
          <Description>PersonalID of the user</Description>
        </AttributeDefinition>
        <AttributeDefinition name="Comment" remediationModificationType="None" type="string">
          <Description>Office number of the user</Description>
        </AttributeDefinition>
        <AttributeDefinition name="WebSite" remediationModificationType="None" type="string">
          <Description>Address of the user Web Page</Description>
        </AttributeDefinition>
        <AttributeDefinition name="PhotoURL" remediationModificationType="None" type="string">
          <Description>Photo URL of the user</Description>
        </AttributeDefinition>
        <AttributeDefinition name="LocalAdmin" remediationModificationType="None" type="string">
          <Description>Local Admin of the user</Description>
        </AttributeDefinition>
        <AttributeDefinition name="CheckPassword" remediationModificationType="None" type="string">
          <Description>Check password of the user</Description>
        </AttributeDefinition>
        <AttributeDefinition name="PasswordChangeInterval" remediationModificationType="None" type="string">
          <Description>Password change interval of the user</Description>
        </AttributeDefinition>
        <AttributeDefinition name="PasswordGracePeriod" remediationModificationType="None" type="string">
          <Description>Password grace period of the user</Description>
        </AttributeDefinition>
        <AttributeDefinition name="Policy" remediationModificationType="None" type="string">
          <Description>Policy of the user</Description>
        </AttributeDefinition>
        <AttributeDefinition name="Profiles" remediationModificationType="None" type="string">
          <Description>Profiles of the user</Description>
        </AttributeDefinition>
        <AttributeDefinition name="ClientType" remediationModificationType="None" type="string">
          <Description>Type of the client</Description>
        </AttributeDefinition>
        <AttributeDefinition name="PostalAddress" remediationModificationType="None" type="string">
          <Description>Postal address of the user</Description>
        </AttributeDefinition>
        <AttributeDefinition name="HomePostalAddress" remediationModificationType="None" type="string">
          <Description>Home postal address of the user</Description>
        </AttributeDefinition>
        <AttributeDefinition name="Street" remediationModificationType="None" type="string">
          <Description>Street of the user</Description>
        </AttributeDefinition>
        <AttributeDefinition name="BusinessCategory" remediationModificationType="None" type="string">
          <Description>Business category of the user</Description>
        </AttributeDefinition>
        <AttributeDefinition name="CarLicense" remediationModificationType="None" type="string">
          <Description>Car license of the user</Description>
        </AttributeDefinition>
        <AttributeDefinition name="DepartmentNumber" remediationModificationType="None" type="string">
          <Description>Department number of the user</Description>
        </AttributeDefinition>
        <AttributeDefinition name="EmployeeNumber" remediationModificationType="None" type="string">
          <Description>Employee number of the user</Description>
        </AttributeDefinition>
        <AttributeDefinition name="EmployeeType" remediationModificationType="None" type="string">
          <Description>Employee type of the user</Description>
        </AttributeDefinition>
        <AttributeDefinition name="SametimeServer" remediationModificationType="None" type="string">
          <Description>Home sametime server of the user</Description>
        </AttributeDefinition>
        <AttributeDefinition name="PasswordChangeDate" remediationModificationType="None" type="string">
          <Description>Password change date of the user</Description>
        </AttributeDefinition>
        <AttributeDefinition name="HTTPPasswordChangeDate" remediationModificationType="None" type="string">
          <Description>HTTP password change date of the user</Description>
        </AttributeDefinition>
        <AttributeDefinition name="NOTEID" remediationModificationType="None" type="string">
          <Description>NOTEID of the user</Description>
        </AttributeDefinition>
        <AttributeDefinition name="$UpdatedBy" remediationModificationType="None" type="string">
          <Description>Name of the user who last updated the user document</Description>
        </AttributeDefinition>
        <AttributeDefinition entitlement="true" managed="true" multi="true" name="Groups" remediationModificationType="None" schemaObjectType="group" type="string">
          <Description>A list of groups of which the user is a member of</Description>
        </AttributeDefinition>
      </Schema>
      <Schema displayAttribute="GroupName" featuresString="GROUPS_HAVE_MEMBERS, PROVISIONING" identityAttribute="ListName" nativeObjectType="group" objectType="group">
        <Attributes>
            <Map>
                <entry key="groupMemberAttribute" value="Members"/>
            </Map>
        </Attributes>
        <AttributeDefinition name="ListName" remediationModificationType="None" type="string">
          <Description>Name of the group</Description>
        </AttributeDefinition>
        <AttributeDefinition name="GroupType" remediationModificationType="None" type="string">
          <Description>Type of the group</Description>
        </AttributeDefinition>
        <AttributeDefinition name="ListDescription" remediationModificationType="None" type="string">
          <Description>Description of the group</Description>
        </AttributeDefinition>
        <AttributeDefinition name="ListOwner" remediationModificationType="None" type="string">
          <Description>Owner of the group</Description>
        </AttributeDefinition>
        <AttributeDefinition name="LocalAdmin" remediationModificationType="None" type="string">
          <Description>Local admin of the group</Description>
        </AttributeDefinition>
        <AttributeDefinition name="MailDomain" remediationModificationType="None" type="string">
          <Description>Mail domain of the group</Description>
        </AttributeDefinition>
        <AttributeDefinition name="InternetAddress" remediationModificationType="None" type="string">
          <Description>Internet address of the group</Description>
        </AttributeDefinition>
        <AttributeDefinition name="Comments" remediationModificationType="None" type="string">
          <Description>Comments about the group</Description>
        </AttributeDefinition>
        <AttributeDefinition name="NOTEID" remediationModificationType="None" type="string">
          <Description>NOTEID of the group</Description>
        </AttributeDefinition>
        <AttributeDefinition name="$UpdatedBy" remediationModificationType="None" type="string">
          <Description>Name of the user who last updated the group document</Description>
        </AttributeDefinition>
      </Schema>
    </Schemas>
    <Templates>
      <Template name="account" schemaObjectType="account" usage="Create">
        <Field displayName="con_form_LDC_server_name" helpKey="help_con_form_LDC_server_name" name="ServerName" required="true" type="string"/>
        <Field displayName="con_form_LDC_use_ca_process" helpKey="help_con_form_LDC_use_ca_process" name="UseCAProcess" reviewRequired="true" type="string" value="N">
          <AllowedValues>
            <String>Y</String>
            <String>N</String>
          </AllowedValues>
        </Field>
        <Field displayName="con_form_LDC_certifier_name" helpKey="help_con_form_LDC_certifier_name" name="CertifierName" reviewRequired="true" type="string"/>
        <Field displayName="con_form_LDC_certifier_id" helpKey="help_con_form_LDC_certifier_id" name="CertifierIDFile" reviewRequired="true" type="string"/>
        <Field displayName="con_form_LDC_certifier_password" helpKey="help_con_form_LDC_certifier_password" name="CertifierPassword" reviewRequired="true" type="secret"/>
        <Field displayName="con_form_LDC_last_name" helpKey="help_con_form_LDC_last_name" name="LastName" required="true" type="string"/>
        <Field displayName="con_form_LDC_user_full_name" helpKey="help_con_form_LDC_user_full_name" name="FullName" required="true" type="string"/>
        <Field displayName="con_form_LDC_user_id" helpKey="help_con_form_LDC_user_id" name="IDFilePath" required="true" type="string"/>
        <Field displayName="con_form_LDC_user_id_password" helpKey="help_con_form_LDC_user_id_password" name="UserIDFilePassword" required="true" type="secret"/>
        <Field displayName="con_form_LDC_id_type" helpKey="help_con_form_LDC_id_type" name="IDType" required="true" type="string" value="HIERARCHICAL">
          <AllowedValues>
            <String>FLAT</String>
            <String>HIERARCHICAL</String>
            <String>CERTIFIER</String>
          </AllowedValues>
        </Field>
      </Template>
      <Template name="Change Password" schemaObjectType="account" usage="ChangePassword">
        <Field displayName="con_prov_policy_http_password" name="HTTP_PASSWORD_CHANGE" reviewRequired="true" section="Please select one or more password types you wish to update" type="string">
          <AllowedValuesDefinition>
            <Value>
              <List>
                <String>Yes</String>
                <String>No</String>
              </List>
            </Value>
          </AllowedValuesDefinition>
         </Field>
        <Field displayName="con_prov_policy_id_vault_password" name="RESET_PASSWORD" reviewRequired="true" section="Please select one or more password types you wish to update" type="string">
          <AllowedValuesDefinition>
            <Value>
              <List>
                <String>Yes</String>
                <String>No</String>
              </List>
            </Value>
          </AllowedValuesDefinition>
         </Field>
         <Field displayName="con_prov_policy_id_file_path" helpKey="help_con_prov_policy_id_file_path" name="IDFilePath" reviewRequired="true" section="Please select one or more password types you wish to update" type="string"/>
      </Template>
      <Template name="group" schemaObjectType="group" usage="Create">
        <Field displayName="con_form_LDC_group_name" helpKey="help_con_form_LDC_group_name" name="ListName" required="true" type="string"/>
      </Template>
      <Template name="group" schemaObjectType="group" usage="Update">
        <Field displayName="con_form_LDC_group_type" helpKey="help_con_form_LDC_group_type" name="GroupType" required="true" type="string" value="Multi-purpose">
          <AllowedValues>
            <String>Multi-purpose</String>
            <String>Mail only</String>
            <String>Access Control List only</String>
            <String>Deny List only</String>
            <String>Servers only</String>
          </AllowedValues>
        </Field>
        <Field displayName="con_form_LDC_list_description" helpKey="help_con_form_LDC_list_description" name="ListDescription" reviewRequired="true" type="string"/>
        <Field displayName="con_form_LDC_list_owner" helpKey="help_con_form_LDC_list_owner" name="ListOwner" reviewRequired="true" type="string"/>
        <Field displayName="con_form_LDC_local_admin" helpKey="help_con_form_LDC_local_admin" name="LocalAdmin" reviewRequired="true" type="string"/>
        <Field displayName="con_form_LDC_mail_domain" helpKey="help_con_form_LDC_mail_domain" name="MailDomain" reviewRequired="true" type="string"/>
        <Field displayName="con_form_LDC_group_net_address" helpKey="help_con_form_LDC_group_net_address" name="InternetAddress" reviewRequired="true" type="string"/>
        <Field displayName="con_form_LDC_group_comments" name="Comments" reviewRequired="true" type="string"/>
      </Template>
    </Templates>
  </Application>
</ImportAction>